TIMESERIESANALYSIS25/__init__.py
TIMESERIESANALYSIS25/gui.py
TIMESERIESANALYSIS25/smoothing.py
TIMESERIESANALYSIS25/stationarity.py
TIMESERIESANALYSIS25-0.1.dist-info/METADATA
TIMESERIESANALYSIS25-0.1.dist-info/WHEEL
TIMESERIESANALYSIS25-0.1.dist-info/top_level.txt
TIMESERIESANALYSIS25-0.1.dist-info/RECORD
